pyblish_lite/__init__.py
pyblish_lite/__main__.py
pyblish_lite/app.css
pyblish_lite/app.py
pyblish_lite/awesome.py
pyblish_lite/compat.py
pyblish_lite/control.py
pyblish_lite/delegate.py
pyblish_lite/mock.py
pyblish_lite/model.py
pyblish_lite/settings.py
pyblish_lite/util.py
pyblish_lite/version.py
pyblish_lite/view.py
pyblish_lite/window.py
pyblish_lite/font/fontawesome/fontawesome-webfont.ttf
pyblish_lite/font/opensans/OpenSans-Bold.ttf
pyblish_lite/font/opensans/OpenSans-BoldItalic.ttf
pyblish_lite/font/opensans/OpenSans-ExtraBold.ttf
pyblish_lite/font/opensans/OpenSans-ExtraBoldItalic.ttf
pyblish_lite/font/opensans/OpenSans-Italic.ttf
pyblish_lite/font/opensans/OpenSans-Light.ttf
pyblish_lite/font/opensans/OpenSans-LightItalic.ttf
pyblish_lite/font/opensans/OpenSans-Regular.ttf
pyblish_lite/font/opensans/OpenSans-Semibold.ttf
pyblish_lite/font/opensans/OpenSans-SemiboldItalic.ttf
pyblish_lite/i18n/zh_CN.qm
pyblish_lite/img/logo-extrasmall.png
pyblish_lite/img/tab-home.png
pyblish_lite/img/tab-overview.png
pyblish_lite/img/tab-terminal.png
pyblish_lite/vendor/Qt.py
pyblish_lite/vendor/__init__.py
pyblish_lite/vendor/six.py
tests/__init__.py
tests/test_control.py
tests/test_model.py
pyblish_lite-0.8.12.dist-info/LICENSE
pyblish_lite-0.8.12.dist-info/METADATA
pyblish_lite-0.8.12.dist-info/WHEEL
pyblish_lite-0.8.12.dist-info/top_level.txt
pyblish_lite-0.8.12.dist-info/RECORD
