Metadata-Version: 1.1
Name: pyblish-lite
Version: 0.8.12
Summary: Lightweight graphical user interface to Pyblish
Home-page: https://github.com/pyblish/pyblish-lite
Author: Abstract Factory and Contributors
Author-email: marcus@abstractfactory.com
License: LGPL
Platform: UNKNOWN
Classifier: Development Status :: 3 - Alpha
Classifier: Intended Audience :: Developers
Classifier: License :: OSI Approved :: GNU Lesser General Public License v3 (LGPLv3)
Classifier: Programming Language :: Python
Classifier: Programming Language :: Python :: 2
Classifier: Programming Language :: Python :: 2.6
Classifier: Programming Language :: Python :: 2.7
Classifier: Programming Language :: Python :: 3.3
Classifier: Programming Language :: Python :: 3.5
Classifier: Topic :: Software Development :: Libraries :: Python Modules
Classifier: Topic :: Utilities
